README.md
setup.cfg
setup.py
Earthquake_scraper/Earthquake_scraper.py
Earthquake_scraper/__init__.py
Earthquake_scraper/scrapeandsave.py
Earthquake_scraper/selection_settings.py
Earthquake_scraper/selectscrapeandsave.py
Earthquake_scraper/upload_file.py
Earthquake_scraper/visit_main_page.py
Earthquake_scraper/rds_uploader/__init__.py
Earthquake_scraper/rds_uploader/rds_uploader.py
Test/__init__.py
Test/test_scrapeandsave.py
Test/test_visit_main_page.py
earthquakescraper.egg-info/PKG-INFO
earthquakescraper.egg-info/SOURCES.txt
earthquakescraper.egg-info/dependency_links.txt
earthquakescraper.egg-info/requires.txt
earthquakescraper.egg-info/top_level.txt
test/test_scrapeandsave.py
test/test_visit_main_page.py