Metadata-Version: 1.0
Name: earthquakescraper
Version: 0.0.1
Summary: Web scraper that scrapes erathquake data from the USGS.
Home-page: https://github.com/Marianna-Karavangeli/Earthquake_scraper.git
Author: Marianna-Karavangeli
Author-email: UNKNOWN
License: MIT
Platform: UNKNOWN
